scapyp/__init__.py
scapyp/autocorr.py
scapyp/batchapply.py
scapyp/case_selection.py
scapyp/cdc.py
scapyp/check_args.py
scapyp/combine.py
scapyp/corrected_tau.py
scapyp/data_processing.py
scapyp/data_transformation.py
scapyp/describe.py
scapyp/dummies_model.py
scapyp/formula_utils.py
scapyp/hplm.py
scapyp/ird.py
scapyp/nap.py
scapyp/outlier_handling.py
scapyp/overlap.py
scapyp/pand.py
scapyp/prepare_data.py
scapyp/rank_transformation.py
scapyp/readdata.py
scapyp/select_case.py
scapyp/singlecasedf.py
scapyp/stat_utils.py
scapyp/trend.py
scapyp/variable_management.py
scapyp-0.1.6.dist-info/LICENSE
scapyp-0.1.6.dist-info/METADATA
scapyp-0.1.6.dist-info/WHEEL
scapyp-0.1.6.dist-info/top_level.txt
scapyp-0.1.6.dist-info/RECORD
